tickle/__init__.py
tickle/agenda.py
tickle/api.py
tickle/cache.py
tickle/cli.py
tickle/dataspec.py
tickle/depend.py
tickle/evaluate.py
tickle/graph.py
tickle/log.py
tickle/util.py
tickle/watch.py
tickle_soren_n-0.4.1.dist-info/LICENSE
tickle_soren_n-0.4.1.dist-info/METADATA
tickle_soren_n-0.4.1.dist-info/WHEEL
tickle_soren_n-0.4.1.dist-info/entry_points.txt
tickle_soren_n-0.4.1.dist-info/top_level.txt
tickle_soren_n-0.4.1.dist-info/RECORD
