Metadata-Version: 2.1
Name: tickle-soren-n
Version: 0.4.1
Summary: A command line workflow automation tool which performs task graph scheduling and concurrent task evaluation.
Home-page: https://github.com/soren-n/tickle
Author: Soren Norbaek
Author-email: sorennorbaek@gmail.com
License: MIT
Platform: UNKNOWN
Classifier: Development Status :: 4 - Beta
Classifier: Environment :: Console
Classifier: Intended Audience :: Developers
Classifier: Intended Audience :: System Administrators
Classifier: License :: OSI Approved :: MIT License
Classifier: Operating System :: MacOS
Classifier: Operating System :: Microsoft
Classifier: Operating System :: POSIX :: Linux
Classifier: Programming Language :: Python :: 3
Classifier: Programming Language :: Python :: 3.9
License-File: LICENSE
Requires-Dist: pyyaml
Requires-Dist: watchdog
